{
  "frames": {
    "icon (1).png": {
      "frame": {
        "x": 2,
        "y": 2,
        "w": 128,
        "h": 128
      },
      "rotated": false,
      "trimmed": false,
      "spriteSourceSize": {
        "x": 0,
        "y": 0,
        "w": 128,
        "h": 128
      },
      "sourceSize": {
        "w": 128,
        "h": 128
      },
      "pivot": {
        "x": 0.5,
        "y": 0.5
      }
    },
    "icon (2).png": {
      "frame": {
        "x": 2,
        "y": 134,
        "w": 128,
        "h": 128
      },
      "rotated": false,
      "trimmed": false,
      "spriteSourceSize": {
        "x": 0,
        "y": 0,
        "w": 128,
        "h": 128
      },
      "sourceSize": {
        "w": 128,
        "h": 128
      },
      "pivot": {
        "x": 0.5,
        "y": 0.5
      }
    },
    "icon (3).png": {
      "frame": {
        "x": 2,
        "y": 266,
        "w": 128,
        "h": 128
      },
      "rotated": false,
      "trimmed": false,
      "spriteSourceSize": {
        "x": 0,
        "y": 0,
        "w": 128,
        "h": 128
      },
      "sourceSize": {
        "w": 128,
        "h": 128
      },
      "pivot": {
        "x": 0.5,
        "y": 0.5
      }
    },
    "icon (4).png": {
      "frame": {
        "x": 2,
        "y": 398,
        "w": 128,
        "h": 128
      },
      "rotated": false,
      "trimmed": false,
      "spriteSourceSize": {
        "x": 0,
        "y": 0,
        "w": 128,
        "h": 128
      },
      "sourceSize": {
        "w": 128,
        "h": 128
      },
      "pivot": {
        "x": 0.5,
        "y": 0.5
      }
    },
    "icon (5).png": {
      "frame": {
        "x": 2,
        "y": 530,
        "w": 128,
        "h": 128
      },
      "rotated": false,
      "trimmed": false,
      "spriteSourceSize": {
        "x": 0,
        "y": 0,
        "w": 128,
        "h": 128
      },
      "sourceSize": {
        "w": 128,
        "h": 128
      },
      "pivot": {
        "x": 0.5,
        "y": 0.5
      }
    },
    "icon (6).png": {
      "frame": {
        "x": 2,
        "y": 662,
        "w": 128,
        "h": 128
      },
      "rotated": false,
      "trimmed": false,
      "spriteSourceSize": {
        "x": 0,
        "y": 0,
        "w": 128,
        "h": 128
      },
      "sourceSize": {
        "w": 128,
        "h": 128
      },
      "pivot": {
        "x": 0.5,
        "y": 0.5
      }
    },
    "icon (7).png": {
      "frame": {
        "x": 2,
        "y": 794,
        "w": 128,
        "h": 128
      },
      "rotated": false,
      "trimmed": false,
      "spriteSourceSize": {
        "x": 0,
        "y": 0,
        "w": 128,
        "h": 128
      },
      "sourceSize": {
        "w": 128,
        "h": 128
      },
      "pivot": {
        "x": 0.5,
        "y": 0.5
      }
    },
    "icon (8).png": {
      "frame": {
        "x": 2,
        "y": 926,
        "w": 128,
        "h": 128
      },
      "rotated": false,
      "trimmed": false,
      "spriteSourceSize": {
        "x": 0,
        "y": 0,
        "w": 128,
        "h": 128
      },
      "sourceSize": {
        "w": 128,
        "h": 128
      },
      "pivot": {
        "x": 0.5,
        "y": 0.5
      }
    },
    "icon (9).png": {
      "frame": {
        "x": 2,
        "y": 1058,
        "w": 128,
        "h": 128
      },
      "rotated": false,
      "trimmed": false,
      "spriteSourceSize": {
        "x": 0,
        "y": 0,
        "w": 128,
        "h": 128
      },
      "sourceSize": {
        "w": 128,
        "h": 128
      },
      "pivot": {
        "x": 0.5,
        "y": 0.5
      }
    },
    "icon.png": {
      "frame": {
        "x": 2,
        "y": 1190,
        "w": 128,
        "h": 128
      },
      "rotated": false,
      "trimmed": false,
      "spriteSourceSize": {
        "x": 0,
        "y": 0,
        "w": 128,
        "h": 128
      },
      "sourceSize": {
        "w": 128,
        "h": 128
      },
      "pivot": {
        "x": 0.5,
        "y": 0.5
      }
    }
  },
  "meta": {
    "app": "http://free-tex-packer.com",
    "version": "0.6.7",
    "image": "heroes_icons_atlas.png",
    "format": "RGBA8888",
    "size": {
      "w": 132,
      "h": 1320
    },
    "scale": 1
  }
}